setup.py
aces/App.py
aces/__init__.py
aces/config.py
aces/default.py
aces/env.py
aces/f.py
aces.egg-info/PKG-INFO
aces.egg-info/SOURCES.txt
aces.egg-info/dependency_links.txt
aces.egg-info/top_level.txt
aces/algorithm/__init__.py
aces/algorithm/cs.py
aces/algorithm/cs1.py
aces/algorithm/jCorrelation.py
aces/algorithm/smooth.py
aces/binary/__init__.py
aces/binary/build.py
aces/binary/setup.py
aces/graph/__init__.py
aces/io/File.py
aces/io/__init__.py
aces/io/lineManager.py
aces/io/lammps/__init__.py
aces/io/lammps/fixAveSpace.py
aces/io/lammps/fixAveTime.py
aces/io/lammps/lammpsdata.py
aces/io/lammps/lammpsdump.py
aces/io/lammps/region.py
aces/io/lammps/strain.py
aces/io/lammps/tempAve.py
aces/io/lammps/velocity.py
aces/io/lammps/velocityh5.py
aces/io/phonopy/__init__.py
aces/io/phonopy/bandplot.py
aces/io/phonopy/dos.py
aces/io/phonopy/fc.py
aces/io/phonopy/phononyaml.py
aces/io/phonopy/pr.py
aces/io/phonopy/qpointsyaml.py
aces/io/vasp/__init__.py
aces/libs/__init__.py
aces/libs/vasp2boltz.py
aces/libs/ElectronicDOS/__init__.py
aces/libs/ElectronicDOS/bands.py
aces/libs/ElectronicDOS/bands_along_z.py
aces/libs/ElectronicDOS/d_band_alignment.py
aces/libs/ElectronicDOS/dos_diff.py
aces/libs/ElectronicDOS/efermi.py
aces/libs/ElectronicDOS/electronicdos.py
aces/libs/ElectronicDOS/plot_atomic_orbital_edos.py
aces/libs/ElectronicDOS/plot_partial_edos.py
aces/libs/ElectronicDOS/plot_partial_orbital_edos.py
aces/libs/ElectronicDOS/plot_single_atom_edos.py
aces/libs/ElectronicDOS/plot_tot_dos.py
aces/libs/pizza/DEFAULTS.py
aces/libs/pizza/POSCAR.py
aces/libs/pizza/__init__.py
aces/libs/pizza/animate.py
aces/libs/pizza/bdump.py
aces/libs/pizza/cdata.py
aces/libs/pizza/cfg.py
aces/libs/pizza/chain.py
aces/libs/pizza/clog.py
aces/libs/pizza/data.py
aces/libs/pizza/dump.py
aces/libs/pizza/ensight.py
aces/libs/pizza/gl.py
aces/libs/pizza/gnu.py
aces/libs/pizza/histo.py
aces/libs/pizza/image.py
aces/libs/pizza/latgen.py
aces/libs/pizza/ldump.py
aces/libs/pizza/log.py
aces/libs/pizza/matlab.py
aces/libs/pizza/mdump.py
aces/libs/pizza/myclass.py
aces/libs/pizza/pair.py
