Metadata-Version: 1.0
Name: aces
Version: 0.17
Summary: A python framework for computational physics numerical experiments.
Home-page: https://github.com/vanceeasleaf/aces
Author: Yang Zhou
Author-email: 404422239@qq.com
License: GPL2.0
Platform: UNKNOWN
